edc_registration/__init__.py
edc_registration/admin.py
edc_registration/admin_site.py
edc_registration/apps.py
edc_registration/auths.py
edc_registration/exceptions.py
edc_registration/modeladmin_mixins.py
edc_registration/modelform_mixins.py
edc_registration/offline_models.py
edc_registration/urls.py
edc_registration/utils.py
edc_registration/migrations/0001_initial.py
edc_registration/migrations/0002_auto_20161127_2226.py
edc_registration/migrations/0003_registeredsubject_subject_type.py
edc_registration/migrations/0004_auto_20161221_0018.py
edc_registration/migrations/0005_auto_20170111_1809.py
edc_registration/migrations/0006_auto_20170209_0924.py
edc_registration/migrations/0007_auto_20170321_1119.py
edc_registration/migrations/0008_auto_20170810_1032.py
edc_registration/migrations/0009_auto_20171228_1816.py
edc_registration/migrations/0010_registeredsubject_consent_datetime.py
edc_registration/migrations/0011_auto_20180116_1411.py
edc_registration/migrations/0012_auto_20180116_1528.py
edc_registration/migrations/0013_auto_20180813_1614.py
edc_registration/migrations/0014_auto_20180814_2017.py
edc_registration/migrations/0015_auto_20181006_2257.py
edc_registration/migrations/0016_historicalregisteredsubject.py
edc_registration/migrations/0017_auto_20190305_0123.py
edc_registration/migrations/0018_auto_20190917_2117.py
edc_registration/migrations/0019_auto_20190922_0439.py
edc_registration/migrations/0020_auto_20191024_1000.py
edc_registration/migrations/0021_auto_20200513_0023.py
edc_registration/migrations/0022_auto_20210801_2021.py
edc_registration/migrations/0023_alter_registeredsubject_options.py
edc_registration/migrations/0024_auto_20220704_1841.py
edc_registration/migrations/0025_auto_20220914_0038.py
edc_registration/migrations/0026_historicalregisteredsubject_familiar_name_and_more.py
edc_registration/migrations/0027_alter_registeredsubject_options.py
edc_registration/migrations/0028_alter_registeredsubject_managers.py
edc_registration-1.0.1.dist-info/licenses/AUTHORS.rst
edc_registration-1.0.1.dist-info/licenses/LICENSE
edc_registration-1.0.1.dist-info/METADATA
edc_registration-1.0.1.dist-info/WHEEL
edc_registration-1.0.1.dist-info/top_level.txt
edc_registration-1.0.1.dist-info/RECORD
